sympasoap/__init__.py
sympasoap/client.py
sympasoap/constants.py
sympasoap/lists.py
sympasoap-1.1.3.dist-info/LICENSE
sympasoap-1.1.3.dist-info/METADATA
sympasoap-1.1.3.dist-info/WHEEL
sympasoap-1.1.3.dist-info/top_level.txt
sympasoap-1.1.3.dist-info/RECORD
